django_eose/__init__.py
django_eose/apps.py
django_eose/executors.py
django_eose/processors.py
django_eose/search.py
django_eose/settings.py
django_eose/utils.py
django_eose-0.3.2.dist-info/licenses/LICENSE
django_eose-0.3.2.dist-info/METADATA
django_eose-0.3.2.dist-info/WHEEL
django_eose-0.3.2.dist-info/top_level.txt
django_eose-0.3.2.dist-info/RECORD
