Metadata-Version: 2.4
Name: django-eose
Version: 0.3.2
Summary: Django Encrypted Object Search Engine.
Author-email: Paulo Otávio Castoldi <paulootavio343@outlook.com>
License: MIT
Project-URL: Homepage, https://github.com/paulootaviodev/django-eose
Keywords: django,search,multiprocessing,decrypted,cache
Classifier: Development Status :: 5 - Production/Stable
Classifier: Intended Audience :: Developers
Classifier: Framework :: Django
Classifier: Framework :: Django :: 5
Classifier: Programming Language :: Python :: 3
Classifier: License :: OSI Approved :: MIT License
Classifier: Operating System :: OS Independent
Requires-Python: >=3.10
License-File: LICENSE
Requires-Dist: Django>=5.2.6
Requires-Dist: sqlparse>=0.5.3
Requires-Dist: asgiref>=3.9.1
Requires-Dist: psutil>=7.0.0
Requires-Dist: cffi>=2.0.0
Requires-Dist: cryptography>=45.0.7
Requires-Dist: pycparser>=2.23
Provides-Extra: dev
Requires-Dist: setuptools>=80.9.0; extra == "dev"
Requires-Dist: wheel>=0.45.1; extra == "dev"
Dynamic: license-file
